Workbook
Name ___________________________________________________________________________________________________________________df1: {#N/A,#N/A,FALSE,"Aging Summary";#N/A,#N/A,FALSE,"Ratio Analysis";#N/A,#N/A,FALSE,"Test 120 Day Accts";#N/A,#N/A,FALSE,"Tickmarks"}
Name _________________________________________________________________________________________________________________df1: {#N/A,#N/A,FALSE,"Aging Summary";#N/A,#N/A,FALSE,"Ratio Analysis";#N/A,#N/A,FALSE,"Test 120 Day Accts";#N/A,#N/A,FALSE,"Tickmarks"}
Name ________________________________________________________________________________________________________________df1: {#N/A,#N/A,FALSE,"Aging Summary";#N/A,#N/A,FALSE,"Ratio Analysis";#N/A,#N/A,FALSE,"Test 120 Day Accts";#N/A,#N/A,FALSE,"Tickmarks"}
Name _______________________________________________________________________________________________________________df1: {#N/A,#N/A,FALSE,"Aging Summary";#N/A,#N/A,FALSE,"Ratio Analysis";#N/A,#N/A,FALSE,"Test 120 Day Accts";#N/A,#N/A,FALSE,"Tickmarks"}
Name _____________________________________________________________________________________________________________df1: {#N/A,#N/A,FALSE,"Aging Summary";#N/A,#N/A,FALSE,"Ratio Analysis";#N/A,#N/A,FALSE,"Test 120 Day Accts";#N/A,#N/A,FALSE,"Tickmarks"}
Name ____________________________________________________________________________________________________________df1: {#N/A,#N/A,FALSE,"Aging Summary";#N/A,#N/A,FALSE,"Ratio Analysis";#N/A,#N/A,FALSE,"Test 120 Day Accts";#N/A,#N/A,FALSE,"Tickmarks"}
Name ___________________________________________________________________________________________________________df1: {#N/A,#N/A,FALSE,"Aging Summary";#N/A,#N/A,FALSE,"Ratio Analysis";#N/A,#N/A,FALSE,"Test 120 Day Accts";#N/A,#N/A,FALSE,"Tickmarks"}
Name _________________________________________________________________________________________________________df1: {#N/A,#N/A,FALSE,"Aging Summary";#N/A,#N/A,FALSE,"Ratio Analysis";#N/A,#N/A,FALSE,"Test 120 Day Accts";#N/A,#N/A,FALSE,"Tickmarks"}
Name ________________________________________________________________________________________________________df1: {#N/A,#N/A,FALSE,"Aging Summary";#N/A,#N/A,FALSE,"Ratio Analysis";#N/A,#N/A,FALSE,"Test 120 Day Accts";#N/A,#N/A,FALSE,"Tickmarks"}
Name _______________________________________________________________________________________________________df1: {#N/A,#N/A,FALSE,"Aging Summary";#N/A,#N/A,FALSE,"Ratio Analysis";#N/A,#N/A,FALSE,"Test 120 Day Accts";#N/A,#N/A,FALSE,"Tickmarks"}
Name ______________________________________________________________________________________________________df1: {#N/A,#N/A,FALSE,"Aging Summary";#N/A,#N/A,FALSE,"Ratio Analysis";#N/A,#N/A,FALSE,"Test 120 Day Accts";#N/A,#N/A,FALSE,"Tickmarks"}
Name _____________________________________________________________________________________________________df1: {#N/A,#N/A,FALSE,"Aging Summary";#N/A,#N/A,FALSE,"Ratio Analysis";#N/A,#N/A,FALSE,"Test 120 Day Accts";#N/A,#N/A,FALSE,"Tickmarks"}
Name ____________________________________________________________________________________________________df1: {#N/A,#N/A,FALSE,"Aging Summary";#N/A,#N/A,FALSE,"Ratio Analysis";#N/A,#N/A,FALSE,"Test 120 Day Accts";#N/A,#N/A,FALSE,"Tickmarks"}
Name __________________________________________________________________________________________________df1: {#N/A,#N/A,FALSE,"Aging Summary";#N/A,#N/A,FALSE,"Ratio Analysis";#N/A,#N/A,FALSE,"Test 120 Day Accts";#N/A,#N/A,FALSE,"Tickmarks"}
Name _________________________________________________________________________________________________df1: {#N/A,#N/A,FALSE,"Aging Summary";#N/A,#N/A,FALSE,"Ratio Analysis";#N/A,#N/A,FALSE,"Test 120 Day Accts";#N/A,#N/A,FALSE,"Tickmarks"}
Name ________________________________________________________________________________________________df1: {#N/A,#N/A,FALSE,"Aging Summary";#N/A,#N/A,FALSE,"Ratio Analysis";#N/A,#N/A,FALSE,"Test 120 Day Accts";#N/A,#N/A,FALSE,"Tickmarks"}
Name _______________________________________________________________________________________________df1: {#N/A,#N/A,FALSE,"Aging Summary";#N/A,#N/A,FALSE,"Ratio Analysis";#N/A,#N/A,FALSE,"Test 120 Day Accts";#N/A,#N/A,FALSE,"Tickmarks"}
Name ______________________________________________________________________________________________df1: {#N/A,#N/A,FALSE,"Aging Summary";#N/A,#N/A,FALSE,"Ratio Analysis";#N/A,#N/A,FALSE,"Test 120 Day Accts";#N/A,#N/A,FALSE,"Tickmarks"}
Name _____________________________________________________________________________________________df1: {#N/A,#N/A,FALSE,"Aging Summary";#N/A,#N/A,FALSE,"Ratio Analysis";#N/A,#N/A,FALSE,"Test 120 Day Accts";#N/A,#N/A,FALSE,"Tickmarks"}
Name ____________________________________________________________________________________________df1: {#N/A,#N/A,FALSE,"Aging Summary";#N/A,#N/A,FALSE,"Ratio Analysis";#N/A,#N/A,FALSE,"Test 120 Day Accts";#N/A,#N/A,FALSE,"Tickmarks"}
Name ___________________________________________________________________________________________df1: {#N/A,#N/A,FALSE,"Aging Summary";#N/A,#N/A,FALSE,"Ratio Analysis";#N/A,#N/A,FALSE,"Test 120 Day Accts";#N/A,#N/A,FALSE,"Tickmarks"}
Name __________________________________________________________________________________________df1: {#N/A,#N/A,FALSE,"Aging Summary";#N/A,#N/A,FALSE,"Ratio Analysis";#N/A,#N/A,FALSE,"Test 120 Day Accts";#N/A,#N/A,FALSE,"Tickmarks"}
Name _________________________________________________________________________________________df1: {#N/A,#N/A,FALSE,"Aging Summary";#N/A,#N/A,FALSE,"Ratio Analysis";#N/A,#N/A,FALSE,"Test 120 Day Accts";#N/A,#N/A,FALSE,"Tickmarks"}
Name ________________________________________________________________________________________df1: {#N/A,#N/A,FALSE,"Aging Summary";#N/A,#N/A,FALSE,"Ratio Analysis";#N/A,#N/A,FALSE,"Test 120 Day Accts";#N/A,#N/A,FALSE,"Tickmarks"}
Name _______________________________________________________________________________________df1: {#N/A,#N/A,FALSE,"Aging Summary";#N/A,#N/A,FALSE,"Ratio Analysis";#N/A,#N/A,FALSE,"Test 120 Day Accts";#N/A,#N/A,FALSE,"Tickmarks"}
Name ______________________________________________________________________________________df1: {#N/A,#N/A,FALSE,"Aging Summary";#N/A,#N/A,FALSE,"Ratio Analysis";#N/A,#N/A,FALSE,"Test 120 Day Accts";#N/A,#N/A,FALSE,"Tickmarks"}
Name _____________________________________________________________________________________df1: {#N/A,#N/A,FALSE,"Aging Summary";#N/A,#N/A,FALSE,"Ratio Analysis";#N/A,#N/A,FALSE,"Test 120 Day Accts";#N/A,#N/A,FALSE,"Tickmarks"}
Name ____________________________________________________________________________________df1: {#N/A,#N/A,FALSE,"Aging Summary";#N/A,#N/A,FALSE,"Ratio Analysis";#N/A,#N/A,FALSE,"Test 120 Day Accts";#N/A,#N/A,FALSE,"Tickmarks"}
Name ___________________________________________________________________________________df1: {#N/A,#N/A,FALSE,"Aging Summary";#N/A,#N/A,FALSE,"Ratio Analysis";#N/A,#N/A,FALSE,"Test 120 Day Accts";#N/A,#N/A,FALSE,"Tickmarks"}
Name __________________________________________________________________________________df1: {#N/A,#N/A,FALSE,"Aging Summary";#N/A,#N/A,FALSE,"Ratio Analysis";#N/A,#N/A,FALSE,"Test 120 Day Accts";#N/A,#N/A,FALSE,"Tickmarks"}
Name _________________________________________________________________________________df1: {#N/A,#N/A,FALSE,"Aging Summary";#N/A,#N/A,FALSE,"Ratio Analysis";#N/A,#N/A,FALSE,"Test 120 Day Accts";#N/A,#N/A,FALSE,"Tickmarks"}
Name ________________________________________________________________________________df1: {#N/A,#N/A,FALSE,"Aging Summary";#N/A,#N/A,FALSE,"Ratio Analysis";#N/A,#N/A,FALSE,"Test 120 Day Accts";#N/A,#N/A,FALSE,"Tickmarks"}
Name ______________________________________________________________________________df1: {#N/A,#N/A,FALSE,"Aging Summary";#N/A,#N/A,FALSE,"Ratio Analysis";#N/A,#N/A,FALSE,"Test 120 Day Accts";#N/A,#N/A,FALSE,"Tickmarks"}
Name _____________________________________________________________________________df1: {#N/A,#N/A,FALSE,"Aging Summary";#N/A,#N/A,FALSE,"Ratio Analysis";#N/A,#N/A,FALSE,"Test 120 Day Accts";#N/A,#N/A,FALSE,"Tickmarks"}
Name ____________________________________________________________________________df1: {#N/A,#N/A,FALSE,"Aging Summary";#N/A,#N/A,FALSE,"Ratio Analysis";#N/A,#N/A,FALSE,"Test 120 Day Accts";#N/A,#N/A,FALSE,"Tickmarks"}
Name ___________________________________________________________________________df1: {#N/A,#N/A,FALSE,"Aging Summary";#N/A,#N/A,FALSE,"Ratio Analysis";#N/A,#N/A,FALSE,"Test 120 Day Accts";#N/A,#N/A,FALSE,"Tickmarks"}
Name __________________________________________________________________________df1: {#N/A,#N/A,FALSE,"Aging Summary";#N/A,#N/A,FALSE,"Ratio Analysis";#N/A,#N/A,FALSE,"Test 120 Day Accts";#N/A,#N/A,FALSE,"Tickmarks"}
Name _________________________________________________________________________df1: {#N/A,#N/A,FALSE,"Aging Summary";#N/A,#N/A,FALSE,"Ratio Analysis";#N/A,#N/A,FALSE,"Test 120 Day Accts";#N/A,#N/A,FALSE,"Tickmarks"}
Name ________________________________________________________________________df1: {#N/A,#N/A,FALSE,"Aging Summary";#N/A,#N/A,FALSE,"Ratio Analysis";#N/A,#N/A,FALSE,"Test 120 Day Accts";#N/A,#N/A,FALSE,"Tickmarks"}
Name _______________________________________________________________________df1: {#N/A,#N/A,FALSE,"Aging Summary";#N/A,#N/A,FALSE,"Ratio Analysis";#N/A,#N/A,FALSE,"Test 120 Day Accts";#N/A,#N/A,FALSE,"Tickmarks"}
Name ______________________________________________________________________df1: {#N/A,#N/A,FALSE,"Aging Summary";#N/A,#N/A,FALSE,"Ratio Analysis";#N/A,#N/A,FALSE,"Test 120 Day Accts";#N/A,#N/A,FALSE,"Tickmarks"}
Name _____________________________________________________________________df1: {#N/A,#N/A,FALSE,"Aging Summary";#N/A,#N/A,FALSE,"Ratio Analysis";#N/A,#N/A,FALSE,"Test 120 Day Accts";#N/A,#N/A,FALSE,"Tickmarks"}
Name ____________________________________________________________________df1: {#N/A,#N/A,FALSE,"Aging Summary";#N/A,#N/A,FALSE,"Ratio Analysis";#N/A,#N/A,FALSE,"Test 120 Day Accts";#N/A,#N/A,FALSE,"Tickmarks"}
Name ___________________________________________________________________df1: {#N/A,#N/A,FALSE,"Aging Summary";#N/A,#N/A,FALSE,"Ratio Analysis";#N/A,#N/A,FALSE,"Test 120 Day Accts";#N/A,#N/A,FALSE,"Tickmarks"}
Name __________________________________________________________________df1: {#N/A,#N/A,FALSE,"Aging Summary";#N/A,#N/A,FALSE,"Ratio Analysis";#N/A,#N/A,FALSE,"Test 120 Day Accts";#N/A,#N/A,FALSE,"Tickmarks"}
Name _________________________________________________________________df1: {#N/A,#N/A,FALSE,"Aging Summary";#N/A,#N/A,FALSE,"Ratio Analysis";#N/A,#N/A,FALSE,"Test 120 Day Accts";#N/A,#N/A,FALSE,"Tickmarks"}
Name ________________________________________________________________df1: {#N/A,#N/A,FALSE,"Aging Summary";#N/A,#N/A,FALSE,"Ratio Analysis";#N/A,#N/A,FALSE,"Test 120 Day Accts";#N/A,#N/A,FALSE,"Tickmarks"}
Name _______________________________________________________________df1: {#N/A,#N/A,FALSE,"Aging Summary";#N/A,#N/A,FALSE,"Ratio Analysis";#N/A,#N/A,FALSE,"Test 120 Day Accts";#N/A,#N/A,FALSE,"Tickmarks"}
Name ______________________________________________________________df1: {#N/A,#N/A,FALSE,"Aging Summary";#N/A,#N/A,FALSE,"Ratio Analysis";#N/A,#N/A,FALSE,"Test 120 Day Accts";#N/A,#N/A,FALSE,"Tickmarks"}
Name _____________________________________________________________df1: {#N/A,#N/A,FALSE,"Aging Summary";#N/A,#N/A,FALSE,"Ratio Analysis";#N/A,#N/A,FALSE,"Test 120 Day Accts";#N/A,#N/A,FALSE,"Tickmarks"}
Name ____________________________________________________________df1: {#N/A,#N/A,FALSE,"Aging Summary";#N/A,#N/A,FALSE,"Ratio Analysis";#N/A,#N/A,FALSE,"Test 120 Day Accts";#N/A,#N/A,FALSE,"Tickmarks"}
Name ___________________________________________________________df1: {#N/A,#N/A,FALSE,"Aging Summary";#N/A,#N/A,FALSE,"Ratio Analysis";#N/A,#N/A,FALSE,"Test 120 Day Accts";#N/A,#N/A,FALSE,"Tickmarks"}
Name _________________________________________________________df1: {#N/A,#N/A,FALSE,"Aging Summary";#N/A,#N/A,FALSE,"Ratio Analysis";#N/A,#N/A,FALSE,"Test 120 Day Accts";#N/A,#N/A,FALSE,"Tickmarks"}
Name ________________________________________________________df1: {#N/A,#N/A,FALSE,"Aging Summary";#N/A,#N/A,FALSE,"Ratio Analysis";#N/A,#N/A,FALSE,"Test 120 Day Accts";#N/A,#N/A,FALSE,"Tickmarks"}
Name ________________________________________________________xlfn.BAHTTEXT: #NAME?
Name _______________________________________________________df1: {#N/A,#N/A,FALSE,"Aging Summary";#N/A,#N/A,FALSE,"Ratio Analysis";#N/A,#N/A,FALSE,"Test 120 Day Accts";#N/A,#N/A,FALSE,"Tickmarks"}
Name _______________________________________________________xlfn.BAHTTEXT: #NAME?
Name ______________________________________________________df1: {#N/A,#N/A,FALSE,"Aging Summary";#N/A,#N/A,FALSE,"Ratio Analysis";#N/A,#N/A,FALSE,"Test 120 Day Accts";#N/A,#N/A,FALSE,"Tickmarks"}
Name ______________________________________________________xlfn.BAHTTEXT: #NAME?
Name _____________________________________________________df1: {#N/A,#N/A,FALSE,"Aging Summary";#N/A,#N/A,FALSE,"Ratio Analysis";#N/A,#N/A,FALSE,"Test 120 Day Accts";#N/A,#N/A,FALSE,"Tickmarks"}

Sheet Executive Summary 
A1: TRUMP TOWERS
A2: INTERNAL FINISHES WORKS
A3: SUMMARY
A4: Sr. No. | B4: Description | C4: Amount | D4: Remarks
A5: A | B5: FINISHING WORK
A6: 1 | B6: FLOORING WORKS | C6: ='BOQ '!I65 -> 0
A7: 2 | B7: CLADDING WORKS | C7: ='BOQ '!I79 -> 0
A8: 3 | B8: PLASTERING | C8: ='BOQ '!I91 -> 0
A9: 4 | B9: PAINTING WORKS | C9: ='BOQ '!I116 -> 0
A10: 5 | B10: CEILING WORKS | C10: ='BOQ '!I125 -> 0
A11: 6 | B11: MISCELLENIOUS WORKS | C11: ='BOQ '!I137 -> 0
B13: TOTAL - A | C13: =SUM(C5:C12) -> 0
A14: B | B14: Tax
B15: GST 18% | C15: =C13*18% -> 0
B16: TOTAL - B | C16: =SUM(C15) -> 0
B18: NET AMOUNT = A + B | C18: =C16+C13 -> 0

Sheet PREAMBLE
A1: Riverday Infrastructure Pvt Ltd
A2: TRUMP TOWER - 69, GURGAON (HARYANA)
A3: PREAMBLE TO of BOQ for TRUMP TOWER Apartment at Sec-69
A4: SR. NO. | B4: DESCRIPTION | C4: REMARKS
B6: The rate for each item of work included in the Bill of Quantities shall, unless expressly stated otherwise, include cost of:
A7: 1 | B7: All items of work covered in this Contract shall be executed strictly as per the requirements detailed in the specifications. Entire execution shall be in total compliance with Specifications, Bill of Quantities,Technical specification, approved drawings(If any) and relevant IS Codes and as per approval of Engineer-in-Charge.
A8: =max($A$4:A7)+1 -> 2 | B8: The unit rate for all Items shall include cost of all taxes (excluding GST & labour cess) and duties and also including packing, forwarding, freight, insurance and transport to site, storage, installation, testing, commissioning,headover and profit, security of material, protection of work till handing over, cleaning, and any other expenses required to complete the works. Rates shall be for all height & levels, Location, Logistics, site HSE, labour welfare, Govt Holidays, inclemently weather, task lighting, scaffolding, tools & tackles including NGT/GRAP ban as per government notifications. This will also applicable for Free issue materials.
A9: =max($A$4:A8)+1 -> 3 | B9: All type of Wastage of materials
A10: =max($A$4:A9)+1 -> 4 | B10: All rates quoted are inclusive of cutting holes and chases in walls and floors and making good the same with adhesive, cement mortar / Gypsum Plaster/ concrete / water proofing etc all specified in drawing / design of appropriate mix and strength as directed by the Engineer-in-Charge. Contractor shall provide holes, sleeves, recesses in the concrete and masonry work as the work proceeds. Quantifying, placing of orders, all wastages, scheduling delivery sequences, taking delivery at ground level and in an area accessible by vehicles, manually, unloading, carrying in, sorting, storing, stripping or clearing off protective wrapping or covering, checking, assembling, returning packing, handling, distributing at various levels and locations, hoisting and placing or lowering in positions, fitting and fixing materials and goods in position, adjusting, refixing and for cutting away and making good, levelling, packing, grouting and pointing with approved materials, providing templates and the like, all in accordance with the generally accepted attendance requirements relating to the specific item, including safeguarding and protection of the works until the issue of the Certificate of Substantial Completion and/or till handing over to end user.
A11: =max($A$4:A10)+1 -> 5 | B11: Liabilities, obligations and risks arising out of Conditions of Contract.
A12: =max($A$4:A11)+1 -> 6 | B12: All requirements of Specifications, whether such requirements are mentioned in the item or not. The Specifications and Drawings where available are to be read as complimentary to and part of the Bill of Quantities and any work called for in one shall be taken as required for all.
A13: =max($A$4:A12)+1 -> 7 | B13: Submission of coordinated shop drawings before start of Works and further execution of works in co-ordination with other agencies as per direction of Engineer-In charge.
A14: =max($A$4:A13)+1 -> 8 | B14: Making all necessary templates, patterns moulds, platforms etc.
A15: =max($A$4:A14)+1 -> 9 | B15: Work in patches, narrow widths, curved surfaces, projected bands set backs, offsets etc.
A16: =max($A$4:A15)+1 -> 10 | B16: Providing grooves, openings, cut-outs, chases & chamfer, edge rounding etc. as per drawing and specification.
A17: =max($A$4:A16)+1 -> 11 | B17: Coordination for all items and other Vendor's Works i.e. MEP works including light fixtures, CP & Sanitary works, AC units, AC grills & Diffusers, Modular Kitchen, Kitchen Sinks, White Goods, Home Automation, Switches, Sockets, DBs, Plumbing and Fire pipelines as direction of Engineer-In charge.
A18: =max($A$4:A17)+1 -> 12 | B18: Scaffolding will be in contractors scope for all lifts and heights.
A19: =max($A$4:A18)+1 -> 13 | B19: The quantities mentioned against each item in BOQ are indicative only. Contractor to provide variation of quantity after getting formal notification to start work, The Contractor shall be paid for the actual quantity of work executed and certified by Engineer-In charge.
... A21: =max($A$4:A20)+1 -> 15 | B21: Tile size given in BOQ are tentative, this may change during execution. No additional charge shall be payable for change in size.
B23: Flooring and wall cladding Specification / Rates shall Include:
A24: =max($A$4:A23)+1 -> 16 | B24: Pre and post sealer Coat suitable for stone at all the edges and surfaces as per direction of Engineer-In charge
A25: =max($A$4:A24)+1 -> 17 | B25: Laying/fixing of Stone/Marble/Tiles etc. in any pattern, shape and sizes as per approved drawing.
A26: =max($A$4:A25)+1 -> 18 | B26: Stonework facing for drop beams of the suspended slabs will be measured same as the item of stone walls unless otherwise is specified in the Bills of Quantities.
A27: =max($A$4:A26)+1 -> 19 | B27: Thickness of stone works given refers to the nominal thickness or the approved thickness by Engineer-in-Charge. No allowance will be made for any additional thickness due to uneven or bad workmanship or to variations in the thickness of the stone
A28: =max($A$4:A27)+1 -> 20 | B28: Shaping of the apparent faces of stones as per drawings and the Instructions of the Architect
A29: =max($A$4:A28)+1 -> 21 | B29: Fabricated wire mesh, dowels, hangers and all tying and fixing tools for stone cladding works as per direction of Engineer- In-Charge
A30: =max($A$4:A29)+1 -> 22 | B30: Pointing including cleaning of stones, scaffolding and dismantling the same and all incidentals. Lintels and other reinforced concrete elements including reinforcement except those elements specified in separate items in the BOQ.
A31: =max($A$4:A30)+1 -> 23 | B31: The rate quoted shall include the cost of all the materials & consumables like Tile, Stone, Cement, Sand, White cement, Pigment, Protection of Flloring etc.
A32: =max($A$4:A31)+1 -> 24 | B32: The stone shall be fixed with mortar in position without the use of chips or under pinning of any sort of deleterious material
A33: =max($A$4:A32)+1 -> 25 | B33: The contractor will arrange verification of all stone lots at source by SDPL representative. Only after due approval , the stone will be procured / transported at site. No lot will be allowed without approval from SDPL. Any type of crack of marble to be fixed with epoxy.
B34: Plastering Works Specification / Methodology / Rates shall Include:
A35: =max($A$4:A34)+1 -> 26 | B35: Gypsum Plaster should pass Standard Compliance IS 2547 (Part I)-1976 for chemical characteristics and IS 2547 (Part II)-1976 for physical characteristics.
A36: =max($A$4:A35)+1 -> 27 | B36: Gypsum plaster should meet technical & physical Parameters like Dry Bulk Density 770 Kg/m3 (Max), Wet Bulk Density 1.35-1.5 g/cm3, Water To Powder Ratio 1:1.25 and thermal resistance R = 0.07m²K/W or as approved by Engineer-in-Charge.
A37: =max($A$4:A36)+1 -> 28 | B37: Junction between straight, raking and curved work are in all cases included with the work in which they occur.
A38: =max($A$4:A37)+1 -> 29 | B38: Certain items are referenced directly to detail drawings to eliminate detailed description. All such reference includes all work to execute the detail.
B40: Carpentry Wood Works Specification / Methodology / Rates shall Include:
A41: =max($A$4:A40)+1 -> 30 | B41: Sizes of timber given in the Bills of Quantities are finished sizes and shall be as per Drawings
A42: =max($A$4:A41)+1 -> 31 | B42: Sizes of doors and other items mentioned in the Bills of Quantities shall allow for tolerance to suit the structural openings as per drawings.
A43: =max($A$4:A42)+1 -> 32 | B43: Work shall include for: Labor, Shop drawings, Any length of timber / board, Joints in the running length of timber / board / Veneer, Raking, curved or circular work and labors, Frames, architrave, chalk holders and other holders and kick plates etc, Allowance for plastering and tiling and the like, Forming holes, angles, ends, miters, rebates, splayed edges, grooves, chamfers, scribed edges, rounded edges, rounded corners, notches, sinkings, fitted ends, far ends and the like, Cutting and fitting around obstructions, Forming moldings, Nosing, bed moulds, margins, and the like, Facing and edging to board / Veneer, Bedding and painting in PU polish as specified, )Grounds, blockings and backings, Plugging concrete, blockwork, and stonework, and making good, installation of all types of ironmongery including cylindrical locks, handles, stoppers, screws, temporarily fixing, re-fixing, oiling and adjusting etc as specified, hardware including nails, screws, dowels, cramps and the like, Steel legs, brackets, bearers and other supports including painting, Glass and glazing including cutting to size and putty, Preparing surfaces to receive finishes, PU Painting // Polishing and the like, to any area or width in any location including work in multicolour and cutting in edges.
A44: =max($A$4:A43)+1 -> 33 | B44: Cost for wooden Flooring to be included with all accessories, edge profiles, skirting etc complete as per drawing, design and specification.
A45: =max($A$4:A44)+1 -> 34 | B45: All Doors to be factory finished, including all cut-outs/punctures for hardware
A46: =max($A$4:A45)+1 -> 35 | B46: The rate shall include providing and applying sealant of approved make to the satisfaction of Client.
A47: =max($A$4:A46)+1 -> 36 | B47: The rate shall include submission of door samples (Frames and shutters), hardware's including mockup and obtaining approval from Client and Architect.
A48: =max($A$4:A47)+1 -> 37 | B48: The description and specification for Wooden Doors, Fire Doors & Glass Doors contained in the Bill of Quantities is indicative and the works shall be fully completed as per the Tender Drawing.
A49: =max($A$4:A48)+1 -> 38 | B49: All the hardware for the doors to be as per the manufacturers recommendation for the size and application of the door. Shop Drgs and Hardware's Schedule to be submitted to Architect & Client for approval prior to execute the job
B52: Ceiling works
A54: =max($A$4:A53)+1 -> 39 | B54: For all ceilings the frame work provided should be sturdy enough to take the load of all services and light fittings as shown in the false ceiling layouts
A55: =max($A$4:A54)+1 -> 40 | B55: Rate to be include all kinds of profiles and cut outs required for light fixtures, speakers, Smoke detector, trap doors and AC grill in the ceiling. Additional framing required for the same to be provided without any extra cost to the owner.
A56: =max($A$4:A55)+1 -> 41 | B56: Only Plan area shall be considered for measurement. No deduction will be made for light fittings, A.C. grilles etc. All wastage will be borne by Contractor.
A57: =max($A$4:A56)+1 -> 42 | B57: The cost for all false ceilings to be inclusive of the following things
B58: a) All associated mock-ups and getting approval from the Architect & Client.
B59: b) Samples to be submitted to the Architect & Client for approval
B62: Painting works
A64: =max($A$4:A63)+1 -> 43 | B64: Rates for painting shall include for the use of different colours to walls, doors, frames and the like and protection and masking of floors, fittings and the like, removing and refixing door and window ironmongery as required.
A65: =max($A$4:A64)+1 -> 44 | B65: Rates for painting pipes and gutters (where such painting is measured separately) shall include for painting all cover plates, fittings, hangers, wall hooks, holderbats, brackets and the like.
A66: =max($A$4:A65)+1 -> 45 | B66: Rates shall include for sample areas showing colours of all paint to be used as and when directed by Engineer-in-Charge/Architect for approval.
A67: =max($A$4:A66)+1 -> 46 | B67: Paint shall be applied as per the specification / Manufacturer’s specification and instructions.
A68: =max($A$4:A67)+1 -> 47 | B68: Minimum Guarantee of TEN 10 Years for all external paints on requisite stamp paper
A69: =max($A$4:A68)+1 -> 48 | B69: All Paints and coatings used in the interiors of the site should have the following VOC content limits. A list of all the paints and Coatings used in the project is to be submitted along with the manufacturer’s certificate for the prescribed VOC limit as per technical specifications and as per as per the LEED requirement and approved by Architect.
A70: =max($A$4:A69)+1 -> 49 | B70: The mode of measurement for painting shall be on the actual surface area of painting without any extra co- efficient. This shall be applicable for all painting works except for all metal railings ( Staircase, Balcony pipe etc) which shall be measured as per IS 1200

Sheet BOQ 
A1: PROJECT: TRUMP TOWERS BILL OF QUANTITIES - FINISHING WORKS
A2: ESTIMATED BILL OF QUANTITIES
A3: Sl.No | B3: Description | C3: UNIT | D3: Basement | E3: T-01 | F3: T-02 | G3: Total Qty | H3: Rate (in Rs) | I3: Amount (in Rs)
A5: A | B5: FLOORING WORKS
A7: 1 | B7: Imported Marble
B8: Providing, stacking, cutting, laying and fixing Imported Marble of approved quality, shade, colour, design, texture and pattern in flooring laid on average 30mm thick cement mortar 1:4 (1 cement : 4 coarse sand) with white cement slury to match the final finished level, joint to be filled with white cement mixed with pigment to match the shade of stone including cutting of stone, surfaces pointing, rubbing, grinding, buffing, Diamond Polishing, approved sealer, curing, protection with 6mm polypropylene sheet until the handing over, making provision for MEP work wherever required, grooves, rebates, reveals, stain & scratch resistance, , for all lead & lift, complete as per specification and drawing up to the satisfaction of Engineer In-Charge.
A9: a | B9: Minimum 18mm thick Imported Marble @ Base Rate FOR at site INR 350/Sft | C9: Sqm | E9: 22331.959 | F9: 22331.959 | G9: =SUM(D9:F9) -> 44663.918 | I9: =G9*H9 -> 0
A11: 2 | B11: Providing, stacking, cutting, laying and fixing Imported Marble of approved quality, shade, colour, design, texture and pattern in skirting over average 12 mm thick cement mortar 1:3 (1 Cement : 3 Coarse Sand) to match the total thickness of wall finish and jointed with cement slurry including Grouting and pointing with white cement paste with pigmented additives matching the shade of the stone. The rate should also be inclusive of surface preparation, cuttng, unloading, shifting to respective floors, hand buffing / cleaning, Diamond Polishing on surface, approved sealer, edge chamfering etc for all lead & lift complete as per directions of Client.
A12: a | B12: Minimum 18mm thick Imported Marble, 75mm high @ Base Rate FOR at site INR 350/Sft | C12: Rmt | E12: 17747.5 | F12: 17747.5 | G12: =SUM(D12:F12) -> 35495 | I12: =G12*H12 -> 0
A14: 3 | B14: Engineered wooden flooring & skirting
B15: Providing and fixing Engineered wooden flooring 14 mm thick , as per approved sample, make, over 5mm thick underlayer polyurethene foam on polythene sheet 250 micron (or as per manufacturer Specification), over a smooth, flat, hard subfloor free from moisture, grease, protection with 6mm polypropylene sheet until the handing over, etc. complete in all respect with requisite accessories like end profile, transition profile, reducer profile, item to be inclusive of cost of 75mm high Engineered Wooden Skirting, including reducer profile, lipping etc, epoxy filling all around of flooring etc. wherever required and preparation of base including all other incidental works for all lead & lift. Quoted rates must include the Engineered wooden flooring accessories. complete as per specification and drawing up to the satisfaction of Engineer In-Charge. (Only plan area to be measured and paid ).
A16: a | B16: Basic rate of material (including Wooden flooring, all required accessories, profiles, skirting, etc.)- INR 250/Sft | C16: Sqm | E16: 11650 | F16: 11650 | G16: =SUM(D16:F16) -> 23300 | I16: =G16*H16 -> 0
A18: 4 | B18: Vitrified Tile
B19: Providing, cutting, laying and fixing Vitrified Tile flooring of approved size, shade & make as approved by Architect laid over average 30mm thick bed of cement mortar 1:4 (1 cement : 4 coarse sand) to match with floor finish level with grey cement slurry, filling the joints with white cement using pigment to match the shade of tile as required, protection with 6mm polypropylene sheet until the handing over, cutting for trap in floor tiles laid as per design, pattern & drawing approved by Architect for various thickness of tiles and for all lead & lift complete up to the satisfaction of Engineer In-Charge.
A20: a | B20: 600x600mm, Matt Finish, Vitrified Tile @ Base Rate FOR at site INR 40/Sft | C20: Sqm | E20: 1470 | F20: 1470 | G20: =SUM(D20:F20) -> 2940 | I20: =G20*H20 -> 0
A21: b | B21: 600x600mm, Vitrified Tile flooring @ Base Rate FOR at site INR 40/Sft | C21: Sqm | D21: 475 | G21: =SUM(D21:F21) -> 475 | I21: =G21*H21 -> 0
A23: =A18+1 -> 5 | B23: Providing, cutting, laying and fixing Vitrified Tile 75mm high skirting of approved size, shade & make as approved by Architect with average 12mm thick cement mortar 1:3 (1 cement : 3 coarse sand) to match with wall finish level with grey cement slurry, filling the joints with white cement using pigment to match the shade of tile as required, for all lead & lift, as per design, pattern & drawing approved by Architect for various thickness of tiles and complete up to the satisfaction of Engineer In-Charge.
A24: a | B24: 600x600mm, Matt Finish, Vitrified Tile @ Base Rate FOR at site INR 40/Sft | C24: Rmt | E24: 2100 | F24: 2100 | G24: =SUM(D24:F24) -> 4200 | I24: =G24*H24 -> 0
A25: b | B25: 600x600mm, Vitrified Tile @ Base Rate FOR at site INR 40/Sft | C25: Rmt | G25: =SUM(D25:F25) -> 0 | I25: =G25*H25 -> 0
A27: 6 | B27: Vitrified Tile
B28: 'Providing, cutting, laying and fixing Vitrified Tile flooring of approved make, size, shade & make as approved by Architect laid over average 30mm thick to match with floor finish level bed of cement mortar 1:4 (1 cement : 4 coarse sand) with grey cement slurry, filling the joints with epoxy grout using pigment to match the shade of tile as required, including 3mm spacer, protection with 6mm polypropylene sheet until the handing over, cutting for floor trap in tiles laid as per design, pattern & drawing approved by Architect for various thick of tiles, for all lead & lift, complete up to the satisfaction of Engineer In-Charge.
A29: a | B29: 285x1800mm, Matt Finish, Vitrified Tile flooring @ Base Rate FOR at site INR 50/Sft | C29: Sqm | E29: 6405 | F29: 6405 | G29: =SUM(D29:F29) -> 12810 | I29: =G29*H29 -> 0
A30: b | B30: 285x1800mm, Matt Finish, Vitrified Tile flooring @ Base Rate FOR at site INR 50/Sft | C30: Sqm | E30: 920 | F30: 920 | G30: =SUM(D30:F30) -> 1840 | I30: =G30*H30 -> 0
A32: 7 | B32: Providing, cutting, laying and fixing Vitrified Tile 75mm high skirting of approved size, shade & make as approved by Architect with average 12mm thick bed of cement mortar 1:3 (1 cement : 3 coarse sand) to match with wall finish level with grey cement slurry, filling the joints with epoxy grout using pigment to match the shade of tile as required, including 3mm spacer, protection with 6mm polypropylene sheet until the handing over, for all lead & lift, as per design, pattern & drawing approved by Architect for various thickness of tiles and complete up to the satisfaction of Engineer In-Charge.
A33: a | B33: 285x1800mm, Matt Finish, Premium Vitrified Tile @ Base Rate FOR at site INR 50/Sft | C33: Rmt | E33: 3840 | F33: 3840 | G33: =SUM(D33:F33) -> 7680 | I33: =G33*H33 -> 0 | K33: 144 | L33: =(H33+H34)/2 -> 0
A34: b | B34: 285x1800mm, Matt Finish, Vitrified Tile @ Base Rate FOR at site INR 50/Sft | C34: Rmt | E34: 1360 | F34: 1360 | G34: =SUM(D34:F34) -> 2720 | I34: =G34*H34 -> 0 | K34: 122
A36: 8 | B36: Staircase Flooring
B37: Providing, cutting and laying full body vitrified Tile specially designed for stair case in specified size, pattern as per design/drawings and specification laid over average 30mm thick cement mortar 1:3 (1 cement : 3 coarse sand) to match the total thickness of floor finish, jointed with cement mixed with pigment to match the shade of tile, making holes if any required complete, as per specification, drawing & direction of Project Manager.
A38: a | B38: Tread & Landing
B39: 300X1250mm Tile @ Base Rate FOR at site INR 80/Sft Note:- Size of tile may vary for landing | C39: Sqm | D39: 1570 | E39: 2611 | F39: 2611 | G39: =SUM(D39:F39) -> 6792 | I39: =G39*H39 -> 0
A41: b | B41: Risers
B42: Item same above but with 12mm thick cement mortar instead of 30mm mortar, '150x1250mm Tile @ Base Rate FOR at site INR 80/Sft | C42: Sqm | D42: 105 | E42: 1286 | F42: 1286 | G42: =SUM(D42:F42) -> 2677 | I42: =G42*H42 -> 0
A44: c | B44: Staircase Skirting 75mm high
B45: Item same as item.no.8 but with 12mm thick cement mortar instead of 30mm mortar, Tile @ Base Rate FOR at site INR 80/Sft | C45: Rmt | D45: 735 | E45: 1647 | F45: 1647 | G45: =SUM(D45:F45) -> 4029 | I45: =G45*H45 -> 0
A47: 9 | B47: Granite Coping
B48: Providing, cutting, laying and fixing minimum 18mm thick prepolished granite stone finish of approved size, shade & make as approved by Architect laid over average 30mm thick bed of cement mortar 1:4 (1 cement : 4 coarse sand) to match with floor finish level with grey cement slurry, filling the joints with white cement using pigment to match the shade of Granite as required including rubbing, buffing, Chamfer, edge polishing, rounding, pattern as per drawing approved by Architect, for all lead & lift complete up to the satisfaction of Engineer In-Charge.
A49: a | B49: Coping to balcony upstands 175mm wide @ Base Rate FOR at site INR 200/Sft | C49: Rmt | E49: 9367 | F49: 9367 | G49: =SUM(D49:F49) -> 18734 | I49: =G49*H49 -> 0
A50: b | B50: Providing, cutting, laying and fixing 18mm thick granite stone finish of approved size, shade & make as approved by Architect laid over 30mm thickness to match with floor finish level bed of cement mortar 1:4 (1 cement : 4 coarse sand) with grey cement slurry, filling the joints with white cement using pigment to match the shade of Granite as required, cutting for trap in floor granite laid as per design, pattern & drawing approved by Architect for various thickness of granite and complete up to the satisfaction of Engineer In-Charge.
B51: Flooring @ Base Rate FOR at site INR 200/Sft | C51: Sqm | E51: 2500 | F51: 2500 | G51: =SUM(D51:F51) -> 5000 | I51: =G51*H51 -> 0
A53: =A47+1 -> 10 | B53: Heat Reflective tiles
B54: Providing, cutting, laying and fixing Heat Reflective tiles of approved size, shade & make as approved by Architect laid over average 30mm thick bed of cement mortar 1:4 (1 cement : 4 coarse sand) to match with floor finish level with grey cement slurry, filling the joints with white cement using pigment to match the shade of tile as required, cutting for trap in floor tiles laid as per design, pattern & drawing approved by Architect , for all lead & lift, complete up to the satisfaction of Engineer In-Charge.
A55: a | B55: Heat Reflective tiles @ Base Rate FOR at site INR 25/Sft | C55: Sqm | E55: 1860 | F55: 1860 | G55: =SUM(D55:F55) -> 3720 | I55: =G55*H55 -> 0
B57: Skirting
A58: b | B58: Item same as item no.10 but with 12mm thick cement mortar instead of 30mm mortar, Tile @ Base Rate FOR at site INR 25/Sft | C58: Rmt | E58: 120 | F58: 120 | G58: =SUM(D58:F58) -> 240 | I58: =G58*H58 -> 0
A60: =A53+1 -> 11 | B60: Kota stone
B61: Providing, cutting, laying and fixing minimum 18mm thick Kota stone of approved size, shade & make as approved by Architect laid over average 30mm thick bed of cement mortar 1:4 (1 cement : 4 coarse sand) to match with floor finish level with grey cement slurry, filling the joints with white cement using pigment to match the shade of Kota as required including rubbing, buffing, polishing, and cutting for trap in floor kota laid as per design, pattern & drawing approved by Architect for various thickness of Kota stone, for all lead & lift, complete up to the satisfaction of Engineer In-Charge. | C61: Sqm | D61: 855 | E61: 400 | F61: 400 | G61: =SUM(D61:F61) -> 1655 | I61: =G61*H61 -> 0
A63: =A60+1 -> 12 | B63: Providing cutting, laying and fixing to pattern, skirting with 75mm high Kota Stone of approved size, color and shade over average 12 mm thick plaster of cement mortar 1:3 (1 Cement : 3 Coarse Sand) to match the total thickness of wall finish and jointing with white cement as per specification/ manufacturer recommendations. Rate to include rubbing, buffing, polishing, etc. complete, with all lead and lift and as per satisfaction & instruction of engineer in charge. | C63: Rmt | D63: 270 | E63: 70 | F63: 70 | G63: =SUM(D63:F63) -> 410 | I63: =G63*H63 -> 0
B65: Sub Total for Section A | I65: =SUM(I6:I64) -> 0
A67: B | B67: CLADDING WORKS
A68: 1 | B68: Providing, cutting, laying and fixing to pattern, Dado on walls with Vitrified Tiles of approved size, color and shade with adhesive of approved make, as per specification/ manufacturer recommendations. Rate to include acid / Soap washing, joint to be filled with white cement with matching color pigment as approved by the Client, etc. complete, with all lead and lift and as directed by Architect/Consultant etc. Cost to include application of Clear sealant at the intersection of the Dado and the Door Frames.
A69: a | B69: 600x1200, Vitrified Tiles @ Base Rate FOR at site INR 40/Sft | C69: Sqm | E69: 2115 | F69: 2115 | G69: =SUM(D69:F69) -> 4230 | I69: =G69*H69 -> 0
A70: b | B70: 1200X1800 Other Toilet Vitrified Tiles @ Base Rate FOR at site INR 120/Sft | C70: Sqm | E70: 12010 | F70: 12010 | G70: =SUM(D70:F70) -> 24020 | I70: =G70*H70 -> 0
A72: 2 | B72: Providing, cutting and fixing Cladding on walls with approved Marble Stone minimum 18mm thick in proper, line, level and alignment machine cut and machine polished stone as mentioned below of approved shade,colour and sample as per the instruction of Consultant & drawings adhesive of approved make , including grouting and pointing with white cement paste with pigmented additives matching the shade of the stone. The rate should also be inclusive of applying temporary supports to the cladded stone as directed by the Consultant surface preparation, cuttng, unloading, shifting to respective floors, hand buffing / cleaning, Polishing on surface, approved sealer, Polished V grooves, inlays, cutting, making drill bit holes and treating the marble as mentioned in the notes above etc, for all lead & lift, complete as per satisfaction of engineer in charge.
A73: a | B73: Imported Marble Stone minimum 18mm thick @ Base Rate FOR at site INR 400/Sft | C73: Sqm | E73: 5949.5 | F73: 5949.5 | G73: =SUM(D73:F73) -> 11899 | I73: =G73*H73 -> 0
A74: b | B74: Imported Marble Stone minimum 18mm thick @ Base Rate FOR at site INR 400/Sft | C74: Sqm | E74: 3542.2648 | F74: 3542.2648 | G74: =SUM(D74:F74) -> 7084.5296 | I74: =G74*H74 -> 0
A76: =A72+1 -> 3 | B76: Providing, cutting, laying & fixing to pattern, of minimum 18mm thick Granite of approved size, color and shade with with adhesive of approved make as per specification/ manufacturer recommendations. Rate to include acid / Soap washing, joints filled with matching color, matching color Epoxy grout of as approved by the Client, etc. complete, with all lead and lift and as directed by Architect/Consultant etc. Cost to include application of Clear sealant at the intersection of the Dado and the Door Frames.
A77: a | B77: Walls @ Base Rate FOR at site INR 200/Sft | C77: Sqm | D77: 633 | E77: 3200 | F77: 3200 | G77: =SUM(D77:F77) -> 7033 | I77: =G77*H77 -> 0
B79: Sub Total for Section B | I79: =SUM(I68:I78) -> 0
A81: C | B81: PLASTERING
B82: Gypsum Plaster on Masonary
A83: 1 | B83: Providing and applying average 12mm thick Gypsum plaster of approved make, on masonry wall surface, jamb, soffit etc as per manufacturer specification finished smooth including the cost of 150GSM fiber mesh on complete surface, including 150mm overlap on RCC surface, scaffolding, making grooves, corner profile, etc. for all lead & lift, complete as per specification and drawing to the complete satisfaction of Engineer In-Charge. | C83: Sqm | E83: 200 | F83: 200 | G83: =SUM(D83:F83) -> 400 | I83: =G83*H83 -> 0
B85: Gypsum Plaster on RCC
A86: 2 | B86: Providing and applying average 12mm thick Gypsum plaster of approved make as per specification, on RCC wall surface, finished smooth including bonding agent of approved make on RCC surface, scaffolding, making grooves, corner profile, etc. for all lead & lift, complete as per specification and drawing to the complete satisfaction of Engineer In-Charge. | C86: Sqm | E86: 98867.5 | F86: 98867.5 | G86: =SUM(D86:F86) -> 197735 | I86: =G86*H86 -> 0
B88: Gypsum Plaster on Ceiling
A89: 3 | B89: Providing and applying average 6mm thick Gypsum plaster on Ceiling surface of approved make to RCC surface as per manufacturer specification finished smooth including bonding agent of approved make on complete RCC surface. scaffolding, making grooves, corner profile, etc. for all lead & lift, complete as per specification and drawing to the complete satisfaction of Engineer In-Charge. | C89: Sqm | E89: 35722.5 | F89: 35722.5 | G89: =SUM(D89:F89) -> 71445 | I89: =G89*H89 -> 0
E90: 0 | F90: 0
B91: Sub Total for Section C | I91: =SUM(I83:I90) -> 0
A93: D | B93: PAINTING WORKS
A95: 1 | B95: Providing and applying two or more coats of Premium Acrylic Emulsion paint of approved make, manufacturer, colour and shade to give a smooth finish on surfaces over two coats of approved putty & 1 coat of primer, including the cost of preparing the surfaces, including thoroughly brushing the surface free from foreign matterial, filling in all holes and cracks and including scaffolding, consumables etc. for all lead & lift, complete as per specification and drawing to the complete satisfaction of Engineer In-Charge.
A96: a) | B96: For Wall | C96: Sqm | E96: 98867.5 | F96: 98867.5 | G96: =SUM(D96:F96) -> 197735 | I96: =G96*H96 -> 0
A98: 2 | B98: Providing and applying two or more coats of Acrylic Emulsion paint of approved make, manufacturer, colour and shade to give a smooth finish on surfaces over two coats of approved putty & 1 coat of primer, including the cost of preparing the surfaces, including thoroughly brushing the surface free from foreign matterial, filling in all holes and cracks and including scaffolding, consumables etc. for all lead & lift, complete as per specification and drawing to the complete satisfaction of Engineer In-Charge.
A99: a) | B99: For Ceiling | C99: Sqm | E99: 35722.5 | F99: 35722.5 | G99: =SUM(D99:F99) -> 71445 | I99: =G99*H99 -> 0
A101: 3 | B101: Providing and applying two or more coats of Oil Bound Distemper paint of approved make, manufacturer, colour and shade to give a smooth finish on surfaces over two coats of approved putty & 1 coat of primer, including the cost of preparing the surfaces, including thoroughly brushing the surface free from foreign matter, filling in all holes and cracks and including scaffolding, consumables etc. for all lead & lift, complete as per specification and drawing to the complete satisfaction of Engineer In-Charge.
A102: a) | B102: For Wall | C102: Sqm | D102: 11700 | E102: 1885 | F102: 1885 | G102: =SUM(D102:F102) -> 15470 | I102: =G102*H102 -> 0
A103: b) | B103: For Ceiling | C103: Sqm | D103: 27845 | E103: 575 | F103: 575 | G103: =SUM(D103:F103) -> 28995 | I103: =G103*H103 -> 0
A105: 4 | B105: Providing and applying 2 or more coats of Exterior Grade Emulsion weather shield paint of approved colour, shade, make, brand, manufacturer, over 2 coats of approved putty & 1 coat of primer, at all heights to give an even shade including thoroughly brushing the surface free from water, mortar droppings and other foreign matter and sand papered smooth, including preparation of surface by thorough cleaning and wetting and applying ready made putty of approved make, including all material and labour, for all lead & lift, the works shall be complete as per specification and directed by the Consultant / Client. (The item includes 10 years warrany on non judicial stamp paper)
A106: a) | B106: For Wall | C106: Sqm | E106: 2285 | F106: 2285 | G106: =SUM(D106:F106) -> 4570 | I106: =G106*H106 -> 0
A107: b) | B107: For Ceiling | C107: Sqm | E107: 7650 | F107: 7650 | G107: =SUM(D107:F107) -> 15300 | I107: =G107*H107 -> 0
E108: 0 | F108: 0
A109: 5 | B109: Providing and applying 2 or more coats of External texture paint of approved make, colour, shade, brand, manufacturer, over 1 coats of approved putty & 1 coat of primer, on any surfaces at all heights to give an even shade including thoroughly brushing the surface free from water, mortar droppings and other foreign matter and sand papered smooth, including preparation of surface by thorough cleaning and wetting and applying ready made putty of approved make, including vertical and horizontal grooves and patterns as directed by engineer in charge, all material and labour, at all floor and heights, the works shall be complete as per specification and directed by the Consultant / Client. (The item includes 10 years warrany on non judicial stamp paper) | E109: 0 | F109: 0
A110: a) | B110: For Wall, Texture Paint@ Applicator Base Rate FOR at site INR 250/Sqm (providing & applying texture paint as per above specification) | C110: Sqm | E110: 4080 | F110: 4080 | G110: =SUM(D110:F110) -> 8160 | I110: =G110*H110 -> 0
E111: 0 | F111: 0
A112: 6 | B112: Providing and applying two coat of Cement-based paint of approved make and shade on wall surfaces, including surface preparation such as cleaning, removal of loose material, curing, as per manufacturer’s specifications, to achieve an even and durable finish as per satisfaction of engineer in charge. | C112: Sqm | D112: 7660 | E112: 21885 | F112: 21885 | G112: =SUM(D112:F112) -> 51430 | I112: =G112*H112 -> 0
A114: 7 | B114: Providing and applying two or more coats of synthetic Enamel paint on RCC/Plastered surface including a coat of approved make primer (including surface preparation like grinding etc), including necessary scaffolding/ staging, etc for all lead & lift, complete as per satisfaction of engineer in charge. | C114: Sqm | D114: 3925 | E114: 3270 | F114: 3270 | G114: =SUM(D114:F114) -> 10465 | I114: =G114*H114 -> 0
B116: Sub Total for Section D | I116: =SUM(I94:I115) -> 0
A118: E | B118: CEILING WORKS
A120: 1 | B120: Gypsum board false ceiling: Providing and fixing 12.5 mm thick tapered edge gypsum plain board conforming to IS: 2095- (Part I) : 2011 (Board with BIS Certification marks) false ceiling at all height including providing and fixing of frame work made of special sections, power pressed from M.S. sheets and galvanized with zinc coating of 120 gms/sqm (both side inclusive) as per IS : 277 and consisting of angle cleats of size 25 mm wide x 1.6 mm thick with flanges of 27 mm and 37mm, at 1200 mm centre to centre, one flange fixed to the ceiling with dash fastener 12.5 mm dia x 50mm long with 6mm dia bolts, other flange of cleat fixed to the angle hangers of 25x10x0.50 mm of required length with nuts & bolts of required size and other end of angle hanger fixed with intermediate G.I. channels 45x15x0.9 mm running at the spacing of 1200 mm centre to centre, to which the ceiling section 0.5 mm thick bottom wedge of 80 mm with tapered flanges of 26 mm each having lips of 10.5 mm, at 450 mm centre to centre, shall be fixed in a direction perpendicular to G.I. intermediate channel with connecting clips made out of 2.64 mm dia x 230 mm long G.I. wire at every junction, including fixing perimeter channels 0.5 mm thick 27 mm high having flanges of 20 mm and 30 mm long, the perimeter of ceiling fixed to wall/partition with the help of rawl plugs at 450 mm centre, with 25mm long dry wall screws @ 230 mm interval, including fixing of gypsum board to ceiling section and perimeter channel with the help of dry wall screws of size 3.5 x 25 mm at 230 mm c/c, including jointing and finishing to a flush finish of tapered and square edges of the board with recommended jointing compound, jointing tapes , finishing with jointing compound in 3 layers covering upto 150 mm on both sides of joint and two coats of primer suitable for board, all as per manufacturer's specification and also including the cost of making openings for light fittings, grills, diffusers, cutouts made with frame of perimeter channels suitably fixed, including making good the surface, all complete as per drawings, specification and direction of the Client. The rate shall includes preparing the surface providing and applying 2 coats of proper putty with primer and painted with approved color / quality of Acrylic emulsion paint ( 2 coats) (Painting works shall be paid separately) with necessary scaffolding at all levels. | C120: Sqm | E120: 1232 | F120: 1232 | G120: =SUM(D120:F120) -> 2464 | I120: =G120*H120 -> 0
B121: MODE OF MEASUREMENT SHALL BE PLAN AREA ONLY, Coves upto 100mm shall not be measured and above that shall be calculated in Sqm and will be paid in same item. Internal cove closing vertical of any height shall be not be measured in any case and shall be part of ceiling only. Note: The Area shall be measured by deducting the trap door plan area which shall be payable in respective item.
A123: 2 | B123: Providing and fixing 12.5mm thick Moisture resistant Gypsum board false ceiling of approved make, which includes Gypsteel surface ribbed perimeter channels (having one flange of 20mm and another flange of 30mm and a web of 27mm) along the perimeter of ceiling, screw fixed to brick wall / partition with the help of nylon sleeves and screws, at 610mm centres. Then suspending Gypsteel surface ribbed intermediate channels of size 45mm (with two flanges of 15mm each) from the soffits at 900mm centres with Gypsteel surface ribbed ceiling angle of width 25mm x 10mm fixed to soffits with GI cleat and steel expansion fasteners. Then Gypsteel surface ribbed ceiling section of having web of 51.5mm and two flanges of 26mm each with lips of 10.5mm are then fixed to the Gypsteel intermediate channel with the help of connecting clip and in direction perpendicular to the Gypsteel intermediate channel at 457 mm centres. for all lead & lift, all material and work as per approved by Engineer in charge. Note: The Area shall be measured by deducting the trap door plan area which shall be payable in respective item. | C123: Sqm | E123: 3495 | F123: 3495 | G123: =SUM(D123:F123) -> 6990 | I123: =G123*H123 -> 0
B125: Sub Total for Section E | I125: =SUM(I119:I124) -> 0
A127: F | B127: MISCELLENIOUS WORKS
A129: 1 | B129: Glass Partition Providing and fixing in position Glass Partition as per approved sample for all lead & lift, Glass area to be measured. Approved makes: As per Approved Sample Glass partition complete set@ Base Rate FOR at site INR 350/Sft | C129: Sqm | E129: 2490 | F129: 2490 | G129: =SUM(D129:F129) -> 4980 | I129: =G129*H129 -> 0
E130: 0 | F130: 0
A131: =A129+1 -> 2 | B131: Trap doors Providing and fixing of trap door as per approved drawing, Access panel (factory fabricated) made out of 24 mm aluminum extruded sections temper 6, 6063 with 80 MICRON JOTUN RAL 9016 powder coating, fixed with 12.5 mm Moisture resistance gypsum board having water absorption less than UP TO 10% core hardness more than 49N and flexural strength longitudinal direction more than 480N, outer frames to have GI 1.5 mm thick connectors, and Heavy duty mini push locks, Safety chain 2 mm high tension steel with safety coating with hook made of GI 4 mm dia, inner frame to have dust seal all around as per manufacturer specifications. 5 years warranty on Power coating Approved make mm2mm Easy access | C131: Nos | E131: 542 | F131: 542 | G131: =SUM(D131:F131) -> 1084 | I131: =G131*H131 -> 0
A133: 3 | B133: Mirror Installation of Back lit, front lit and Bevelled mirror at Wash Basins Counters of size as per drawings & specification, including all required hardwares and necessary fixtures for fixing of mirrors as per approved make and as approved by Client for all lead & lift as per instruction of engineer in charge. (Mirror Will be provied free of Cost)
B134: Size Upto 1.5M ( Including 1.5M) | C134: Nos | E134: 586 | F134: 586 | G134: =SUM(D134:F134) -> 1172 | I134: =G134*H134 -> 0
B135: Size Above 1.5M | C135: Nos | E135: 105 | F135: 105 | G135: =SUM(D135:F135) -> 210 | I135: =G135*H135 -> 0
B137: Sub Total for Section F | I137: =SUM(I128:I136) -> 0
B138: Total | I138: =I65+I79+I91+I116+I125+I137 -> 0
